apixoo/__init__.py
apixoo/const.py
apixoo/pixel_bean.py
apixoo/pixel_bean_decoder.py
APIxoo-0.3.1.dist-info/LICENSE.md
APIxoo-0.3.1.dist-info/METADATA
APIxoo-0.3.1.dist-info/WHEEL
APIxoo-0.3.1.dist-info/top_level.txt
APIxoo-0.3.1.dist-info/RECORD
