Metadata-Version: 2.1
Name: APIxoo
Version: 0.3.1
Summary: Python wrapper for Divoom Pixoo server API
Home-page: https://github.com/redphx/apixoo
Download-URL: https://github.com/redphx/apixoo
Author: redphx
License: MIT
Keywords: apixoo,divoom,pixoo,pixoo64
Platform: any
Classifier: Intended Audience :: Developers
Classifier: Topic :: Software Development
Classifier: Programming Language :: Python
Requires-Python: >3.6
License-File: LICENSE.md
Requires-Dist: requests
